yy_core/__init__.py
yy_core/base_model.py
yy_core/cache_model.py
yy_core/coding.py
yy_core/config.py
yy_core/crypto.py
yy_core/csv.py
yy_core/excel.py
yy_core/file.py
yy_core/host.py
yy_core/http.py
yy_core/json.py
yy_core/log.py
yy_core/mysql.py
yy_core/os.py
yy_core/redis.py
yy_core/share_config.py
yy_core/time.py
yy_core/uuid.py
yy_core/console/__init__.py
yy_core/console/base_console.py
yy_core/console/stat_console_model.py
yy_core/handlers/__init__.py
yy_core/handlers/core.py
yy_core/handlers/filter_base.py
yy_core/handlers/frame_base.py
yy_core/handlers/client/__init__.py
yy_core/handlers/client/address.py
yy_core/handlers/client/order.py
yy_core/handlers/client/task.py
yy_core/handlers/client/user.py
yy_core/handlers/server/__init__.py
yy_core/handlers/server/goods_s.py
yy_core/handlers/server/ip_s.py
yy_core/handlers/server/order_s.py
yy_core/handlers/server/price_s.py
yy_core/handlers/server/report_s.py
yy_core/handlers/server/task_s.py
yy_core/handlers/server/user_s.py
yy_core/libs/__init__.py
yy_core/libs/customize/__init__.py
yy_core/libs/customize/core_helper.py
yy_core/libs/customize/cryptography_helper.py
yy_core/libs/customize/file_helper.py
yy_core/libs/customize/safe_helper.py
yy_core/libs/customize/wechat_helper.py
yy_core/models/__init__.py
yy_core/models/act_base_model.py
yy_core/models/app_base_model.py
yy_core/models/asset_base_model.py
yy_core/models/core_model.py
yy_core/models/enum.py
yy_core/models/frame_base_model.py
yy_core/models/ip_base_model.py
yy_core/models/order_base_model.py
yy_core/models/price_base_model.py
yy_core/models/stat_base_model.py
yy_core/models/task_base_model.py
yy_core/models/top_base_model.py
yy_core/models/user_base_model.py
yy_core/models/db_models/__init__.py
yy_core/models/db_models/act/__init__.py
yy_core/models/db_models/act/act_info_model.py
yy_core/models/db_models/act/act_module_model.py
yy_core/models/db_models/app/__init__.py
yy_core/models/db_models/app/app_info_model.py
yy_core-1.0.11.dist-info/licenses/LICENSE
yy_core-1.0.11.dist-info/METADATA
yy_core-1.0.11.dist-info/WHEEL
yy_core-1.0.11.dist-info/top_level.txt
yy_core-1.0.11.dist-info/RECORD
