Metadata-Version: 2.4
Name: yy_core
Version: 1.0.11
Summary: yy_core
Home-page: 
Author: yy
Author-email: yy@qq.com
License: MIT
Classifier: Topic :: Software Development :: Libraries :: Python Modules
Classifier: Programming Language :: Python
Classifier: Programming Language :: Python :: 3.4
Classifier: Programming Language :: Python :: 3.5
Classifier: Programming Language :: Python :: 3.5
Classifier: Programming Language :: Python :: 3.6
Classifier: Programming Language :: Python :: 3.7
Classifier: Programming Language :: Python :: 3.8
Classifier: Programming Language :: Python :: 3.9
Requires-Python: ~=3.4
License-File: LICENSE
Requires-Dist: asq==1.3
Requires-Dist: emoji==1.6.1
Requires-Dist: xmltodict==0.12.0
Requires-Dist: requests==2.32.3
Requires-Dist: requests-pkcs12==1.25
Requires-Dist: mmh3==3.0.0
Requires-Dist: bce-python-sdk==0.8.61
Dynamic: author
Dynamic: author-email
Dynamic: classifier
Dynamic: description
Dynamic: description-content-type
Dynamic: license
Dynamic: license-file
Dynamic: requires-dist
Dynamic: requires-python
Dynamic: summary
